cnparser/__init__.py
cnparser/enrich.py
cnparser/load.py
cnparser/utility.py
cnparser/config/file_id.json
cnparser/config/header.json
cnparser/config/kind.json
cnparser/config/legal_entity.json
cnparser-1.7.0.dist-info/licenses/LICENSE
test/__init__.py
test/test_enrich.py
test/test_load.py
cnparser-1.7.0.dist-info/METADATA
cnparser-1.7.0.dist-info/WHEEL
cnparser-1.7.0.dist-info/top_level.txt
cnparser-1.7.0.dist-info/RECORD
