Metadata-Version: 2.4
Name: cnparser
Version: 1.7.0
Summary: cnparser is a parser library of Corporate Number Publication Site data.
Home-page: https://github.com/new-village/cnparser
Author: new-village
License: Apache-2.0 license
License-File: LICENSE
Requires-Dist: requests
Requires-Dist: bs4
Requires-Dist: pandas
Requires-Dist: pandarallel
Requires-Dist: pykakasi
Dynamic: author
Dynamic: description
Dynamic: description-content-type
Dynamic: home-page
Dynamic: license
Dynamic: license-file
Dynamic: requires-dist
Dynamic: summary
